key_generator/key_generator.py
key_generator-1.0.3.dist-info/LICENSE
key_generator-1.0.3.dist-info/METADATA
key_generator-1.0.3.dist-info/WHEEL
key_generator-1.0.3.dist-info/top_level.txt
key_generator-1.0.3.dist-info/RECORD
