Metadata-Version: 2.1
Name: key_generator
Version: 1.0.3
Summary: A Simple python package to generate customizable keys.
Home-page: https://github.com/Sahith02/key-generator
Author: Sahith Kurapati
Author-email: sahith02@gmail.com
License: MIT
Platform: UNKNOWN
Classifier: License :: OSI Approved :: MIT License
Classifier: Programming Language :: Python :: 2
Classifier: Programming Language :: Python :: 2.7
Classifier: Programming Language :: Python :: 3
Classifier: Programming Language :: Python :: 3.7
